grpc_google_cloud_speech_v1beta1-1.0.1-py2.7-nspkg.pth
google/cloud/speech/v1beta1/__init__.py
google/cloud/speech/v1beta1/cloud_speech_pb2.py
google/longrunning/__init__.py
google/longrunning/operations_grpc_pb2.py
grpc_google_cloud_speech_v1beta1-1.0.1.dist-info/DESCRIPTION.rst
grpc_google_cloud_speech_v1beta1-1.0.1.dist-info/METADATA
grpc_google_cloud_speech_v1beta1-1.0.1.dist-info/RECORD
grpc_google_cloud_speech_v1beta1-1.0.1.dist-info/WHEEL
grpc_google_cloud_speech_v1beta1-1.0.1.dist-info/metadata.json
grpc_google_cloud_speech_v1beta1-1.0.1.dist-info/namespace_packages.txt
grpc_google_cloud_speech_v1beta1-1.0.1.dist-info/top_level.txt
