Metadata-Version: 2.0
Name: grpc-google-cloud-speech-v1beta1
Version: 1.0.1
Summary: GRPC library for service grpc-google-cloud-speech-v1beta1
Home-page: https://github.com/google/googleapis
Author: Google Inc
Author-email: googleapis-packages@google.com
License: Apache-2.0
Platform: UNKNOWN
Classifier: Intended Audience :: Developers
Classifier: Development Status :: 4 - Beta
Classifier: Intended Audience :: Developers
Classifier: License :: OSI Approved :: Apache Software License
Classifier: Programming Language :: Python
Classifier: Programming Language :: Python :: 2.7
Classifier: Programming Language :: Python :: Implementation :: CPython
Requires-Dist: googleapis-common-protos (>=1.1.0)
Requires-Dist: grpcio (>=0.13.0)
Requires-Dist: oauth2client (>=1.4.11)
